{
    "title": "Easy: String Reverse",
    "description": "A string reverse problem where the input string is reversed and returned. Write a function `reverse_string` that takes a string as an argument and returns it reversed.\n\n#### Function Signature\n```python\ndef reverse_string(s: str) -> str:\n```\n\n#### Input\n- `s` (str): A string that may contain letters, numbers, spaces, and punctuation.\n\n#### Output\n- Returns the input string `s` reversed.\n",
    "code": "def reverse_string(s: str) -> str:\n    return s[::-1]\n",
    "tests": [
        "assert reverse_string(\"hello\") == \"olleh\"",
        "assert reverse_string(\"world\") == \"dlrow\"",
        "assert reverse_string(\"1234567890\") == \"0987654321\"",
        "assert reverse_string(\"!@#$%^&*()\") == \")(*&^%$#@!\""
    ],
    "difficulty": "hard",
    "model": "codegeex4:9b",
    "style": "HackerRank"
}